LICENSE
robox/__init__.py
robox/_client.py
robox/_controls.py
robox/_download.py
robox/_exceptions.py
robox/_form.py
robox/_history.py
robox/_link.py
robox/_options.py
robox/_page.py
robox/_retry.py
robox/_robots.py
robox/_table.py
robox/py.typed
robox-0.2.3.dist-info/LICENSE
robox-0.2.3.dist-info/WHEEL
robox-0.2.3.dist-info/METADATA
robox-0.2.3.dist-info/RECORD
