Metadata-Version: 2.1
Name: robox
Version: 0.2.3
Summary: Robox is a simple library for exploring/scraping the web or testing a website you’re developing.
Home-page: https://github.com/danclaudiupop/robox
License: BSD 3
Keywords: httpx,scraping,testing
Author: Dan Claudiu Pop
Author-email: danclaudiupop@gmail.com
Requires-Python: >=3.8,<4.0
Classifier: Development Status :: 3 - Alpha
Classifier: Environment :: Web Environment
Classifier: Framework :: AsyncIO
Classifier: Framework :: Trio
Classifier: Intended Audience :: Developers
Classifier: License :: OSI Approved :: BSD License
Classifier: License :: Other/Proprietary License
Classifier: Operating System :: OS Independent
Classifier: Programming Language :: Python :: 3
Classifier: Programming Language :: Python :: 3 :: Only
Classifier: Programming Language :: Python :: 3.10
Classifier: Programming Language :: Python :: 3.8
Classifier: Programming Language :: Python :: 3.9
Classifier: Topic :: Internet :: WWW/HTTP
Requires-Dist: aiofiles (>=0.8.0,<0.9.0)
Requires-Dist: beautifulsoup4 (>=4.9.3,<5.0.0)
Requires-Dist: httpx (>=0.21.1,<0.22.0)
Requires-Dist: httpx-cache (>=0.4.0,<0.5.0)
Requires-Dist: tenacity (>=8.0.1,<9.0.0)
Project-URL: Repository, https://github.com/danclaudiupop/robox
